unofficial_ascend_tools/__init__.py
unofficial_ascend_tools/embeddings/__init__.py
unofficial_ascend_tools/embeddings/ascend.py
unofficial_ascend_tools-0.0.3.dist-info/LICENSE
unofficial_ascend_tools-0.0.3.dist-info/METADATA
unofficial_ascend_tools-0.0.3.dist-info/WHEEL
unofficial_ascend_tools-0.0.3.dist-info/top_level.txt
unofficial_ascend_tools-0.0.3.dist-info/RECORD
