Metadata-Version: 2.1
Name: unofficial-ascend-tools
Version: 0.0.3
Summary: unofficial-ascend-tools
Home-page: https://gitee.com/yuncliu/unofficial-ascend-tools
License: Apache
Classifier: Programming Language :: Python :: 3
Classifier: License :: OSI Approved :: Apache Software License
Classifier: Operating System :: OS Independent
Requires-Python: >= 3.7
License-File: LICENSE
